aws_sso/__init__.py
aws_sso/__main__.py
aws_sso/credentials.py
aws_sso/file_handler.py
aws_sso/helper.py
aws_sso/sso_util.py
tests/__init__.py
tests/credentials_test.py
tests/file_handler_test.py
tests/helper_test.py
tests/main_test.py
aws_sso_credential_provider-1.0.0.dist-info/LICENSE
aws_sso_credential_provider-1.0.0.dist-info/METADATA
aws_sso_credential_provider-1.0.0.dist-info/WHEEL
aws_sso_credential_provider-1.0.0.dist-info/top_level.txt
aws_sso_credential_provider-1.0.0.dist-info/RECORD
