Metadata-Version: 2.1
Name: aws-sso-credential-provider
Version: 1.0.0
Summary: Session credential provider for AWS SSO roles
Home-page: https://github.com/kcerdena/aws_sso
Author: Kacey Cerdena
Author-email: 6180729+kcerdena@users.noreply.github.com
License: UNKNOWN
Platform: UNKNOWN
Classifier: Programming Language :: Python :: 3.6
Classifier: Programming Language :: Python :: 3.7
Classifier: Programming Language :: Python :: 3.8
Classifier: License :: OSI Approved :: GNU General Public License v3 (GPLv3)
Classifier: Operating System :: POSIX
Classifier: Topic :: System :: Systems Administration
Requires-Python: >=3.6
Requires-Dist: python-dateutil (>=2.8)
Requires-Dist: boto3 (>=1.13)
